{
	"stato": "ok",
	"risultato": {
		"titolo": "Dashboard",
		"toolbar": {},
		"breadcrumbs": {},
		"flashbag": {},
		"widgets": [{
			"titolo": "Lista clienti",
			"columns": 4,
			"drag": false,
			"collapse": true,
			"minimize": false,
			"tabs": [{
				"comando": "getGenericWithSchema",
				"parametri": {
					"$entity": "anagraficiPersona",
					"orderBy": []
				}
			}]
		}, {
			"titolo": "Lista 2",
			"columns": 8,
			"drag": false,
			"collapse": false,
			"minimize": false,
			"tabs": [{
				"comando": "getGenericWithSchema",
				"parametri": {
					"$entity": "anagraficiPersona",
					"orderBy": []
				}
			}]
		}],
		"data": [{
			"view": "asdlksjdalkdjjas234339sd[asd]-ass"
		}, {
			"view": "asdlksjdalkdjjas234339sd[asd]-ass"
		}, {
			"list": "asdlksjdalkdjjas234339sd[asd]-ass"
		}]
	}
}